openspoor/.git_keep
openspoor/__init__.py
openspoor/config.yaml
openspoor/py.typed
openspoor/mapservices/MapservicesQuery.py
openspoor/mapservices/PUICMapservices.py
openspoor/mapservices/__init__.py
openspoor/mapservices/find_mapservice.py
openspoor/network/__init__.py
openspoor/network/trackgraph.py
openspoor/spoortakmodel/__init__.py
openspoor/spoortakmodel/spoortak_model_inspector.py
openspoor/spoortakmodel/spoortak_model_mapper.py
openspoor/spoortakmodel/spoortak_models_data.py
openspoor/spoortakmodel/spoortak_subsection.py
openspoor/transformers/TransformerCoordinatesToSpoor.py
openspoor/transformers/TransformerGeocodeToCoordinates.py
openspoor/transformers/TransformerSpoortakToCoordinates.py
openspoor/transformers/__init__.py
openspoor/utils/__init__.py
openspoor/utils/common.py
openspoor/utils/safe_requests.py
openspoor/utils/singleton.py
openspoor/visualisations/__init__.py
openspoor/visualisations/route.py
openspoor/visualisations/trackmap.py
openspoor-0.3.4.dist-info/METADATA
openspoor-0.3.4.dist-info/WHEEL
openspoor-0.3.4.dist-info/licenses/LICENSE
openspoor-0.3.4.dist-info/RECORD
