Metadata-Version: 2.4
Name: openspoor
Version: 0.3.4
Summary: Open source project to allow translations between different spoor referential systems
Author-email: Your Name <your.email@example.com>
License-Expression: MIT
License-File: LICENSE
Requires-Python: <4,>=3.10
Requires-Dist: fiona<2,>=1.10.1
Requires-Dist: folium<0.20,>=0.19.4
Requires-Dist: geopandas<2,>=1.0.1
Requires-Dist: importlib-metadata<9,>=8.6.1
Requires-Dist: loguru<0.8,>=0.7.3
Requires-Dist: numpy<3,>=2.2.3
Requires-Dist: pandas<3,>=2.2.3
Requires-Dist: parameterized<0.10,>=0.9.0
Requires-Dist: pyproj<4,>=3.7.1
Requires-Dist: pyyaml<7,>=6.0.2
Requires-Dist: requests<3,>=2.32.3
Requires-Dist: shapely<3,>=2.0.7
Requires-Dist: types-geopandas>=1.0.1.20250120
Requires-Dist: types-pyyaml<7,>=6.0.12.20241230
Requires-Dist: types-requests<3,>=2.32.0.20241016
